django/__init__.py
django/__main__.py
django/shortcuts.py
django/apps/__init__.py
django/apps/config.py
django/apps/registry.py
django/conf/__init__.py
django/conf/global_settings.py
django/conf/locale/__init__.py
django/conf/locale/ar/__init__.py
django/conf/locale/ar/formats.py
django/conf/locale/az/__init__.py
django/conf/locale/az/formats.py
django/conf/locale/bg/__init__.py
django/conf/locale/bg/formats.py
django/conf/locale/bn/__init__.py
django/conf/locale/bn/formats.py
django/conf/locale/bs/__init__.py
django/conf/locale/bs/formats.py
django/conf/locale/ca/__init__.py
django/conf/locale/ca/formats.py
django/conf/locale/cs/__init__.py
django/conf/locale/cs/formats.py
django/conf/locale/cy/__init__.py
django/conf/locale/cy/formats.py
django/conf/locale/da/__init__.py
django/conf/locale/da/formats.py
django/conf/locale/de/__init__.py
django/conf/locale/de/formats.py
django/conf/locale/de_CH/__init__.py
django/conf/locale/de_CH/formats.py
django/conf/locale/el/__init__.py
django/conf/locale/el/formats.py
django/conf/locale/en/__init__.py
django/conf/locale/en/formats.py
django/conf/locale/en_AU/__init__.py
django/conf/locale/en_AU/formats.py
django/conf/locale/en_GB/__init__.py
django/conf/locale/en_GB/formats.py
django/conf/locale/eo/__init__.py
django/conf/locale/eo/formats.py
django/conf/locale/es/__init__.py
django/conf/locale/es/formats.py
django/conf/locale/es_AR/__init__.py
django/conf/locale/es_AR/formats.py
django/conf/locale/es_CO/__init__.py
django/conf/locale/es_CO/formats.py
django/conf/locale/es_MX/__init__.py
django/conf/locale/es_MX/formats.py
django/conf/locale/es_NI/__init__.py
django/conf/locale/es_NI/formats.py
django/conf/locale/es_PR/__init__.py
django/conf/locale/es_PR/formats.py
django/conf/locale/et/__init__.py
django/conf/locale/et/formats.py
django/conf/locale/eu/__init__.py
django/conf/locale/eu/formats.py
django/conf/locale/fa/__init__.py
django/conf/locale/fa/formats.py
django/conf/locale/fi/__init__.py
django_linux-2.2.8.dist-info/METADATA
django_linux-2.2.8.dist-info/WHEEL
django_linux-2.2.8.dist-info/top_level.txt
django_linux-2.2.8.dist-info/RECORD
