Metadata-Version: 2.1
Name: django-linux
Version: 2.2.8
Summary: A high-level Python Web framework that encourages rapid development and clean, pragmatic design. 
Home-page: https://github.com/NocoldBob/Django
Author: fastbiubiu
Author-email: fastbiubiu@163.com
License: UNKNOWN
Platform: UNKNOWN
Classifier: Programming Language :: Python :: 3
Classifier: License :: OSI Approved :: MIT License
Classifier: Operating System :: OS Independent
